Metadata-Version: 1.0
Name: simplelayout-githubmonsidian
Version: 0.1
Summary: 再来一碗
Home-page: https://github.com/idrl-assignment/3-simplelayout-package-monsidian
Author: LongYutong
Author-email: 403216817@qq.com
License: UNKNOWN
Platform: UNKNOWN
